codewars_test/__init__.py
codewars_test/test_framework.py
codewars_test_teey-0.1.0.dist-info/LICENSE.md
codewars_test_teey-0.1.0.dist-info/METADATA
codewars_test_teey-0.1.0.dist-info/WHEEL
codewars_test_teey-0.1.0.dist-info/top_level.txt
codewars_test_teey-0.1.0.dist-info/RECORD
