Metadata-Version: 2.1
Name: codewars_test_teey
Version: 0.1.0
Summary: Codewars test framework for Python (fork)
Home-page: https://github.com/teey-t/python-test-framework
Author: Codewars
License: MIT
Platform: UNKNOWN
Classifier: Programming Language :: Python :: 3
Classifier: License :: OSI Approved :: MIT License
Classifier: Operating System :: OS Independent
Requires-Python: >=3.6
